[{"__isset":{"RoadLine":true,"Updown":true,"RoadTrend":true,"SellTicketModus":true,"LineLength":true,"StationCount":true,"WholeDriveTime":true,"Interval":true,"StationClassFindList":true,"Linelatlon":true,"TicketPrice":true},"RoadLine":"1804路","Updown":0,"RoadTrend":"自松江客运中心起经嘉松南路、广富林路、龙马路、梅家浜路、人民北路、文汇路、龙源路、文翔路、三新北路、广富林路、龙源路、文汇路、人民北路、梅家浜路、嘉松南路至松江客运中心。","SellTicketModus":"无人","LineLength":13.8,"StationCount":26,"WholeDriveTime":"","Interval":"","StationClassFindList":[{"__isset":{"StationName":true,"Updown":true,"SeTime":true,"StationAddress":true,"Stationcode":true,"StrLon02":true,"StrLat02":true,"AssetNumber":true,"LINELIST":true},"StationName":"客运中心北站","Updown":0,"SeTime":"21:00-00:11","StationAddress":"大学城地铁站","Stationcode":"SJ0669","StrLon02":121.237355,"StrLat02":31.054684,"AssetNumber":"","LINELIST":"1803路、1804路、松江13路、松江16路、松江21路、松江24路、松江3路、松江66路、松江7路、松江9路"},{"__isset":{"StationName":true,"Updown":true,"SeTime":true,"StationAddress":true,"Stationcode":true,"StrLon02":true,"StrLat02":true,"AssetNumber":true,"LINELIST":true},"StationName":"广富林路嘉松公路","Updown":0,"SeTime":"21:01-00:12","StationAddress":"嘉松公路广富林路交叉口西50米","Stationcode":"SJ0701","StrLon02":121.23597,"StrLat02":31.057457,"AssetNumber":"","LINELIST":"1804路、松江13路、松江15路"},{"__isset":{"StationName":true,"Updown":true,"SeTime":true,"StationAddress":true,"Stationcode":true,"StrLon02":true,"StrLat02":true,"AssetNumber":true,"LINELIST":true},"StationName":"龙马路广富林路","Updown":0,"SeTime":"21:03-00:14","StationAddress":"龙马路181号附近","Stationcode":"SJ3423","StrLon02":121.231786,"StrLat02":31.056276,"AssetNumber":"","LINELIST":"1804路、松江24路"},{"__isset":{"StationName":true,"Updown":true,"SeTime":true,"StationAddress":true,"Stationcode":true,"StrLon02":true,"StrLat02":true,"AssetNumber":true,"LINELIST":true},"StationName":"梅家浜路人民北路","Updown":0,"SeTime":"21:05-00:16","StationAddress":"龙马路梅家浜路交叉口西100米","Stationcode":"SJ0710","StrLon02":121.230164,"StrLat02":31.052466,"AssetNumber":"","LINELIST":"1802路、1804路、松江18路、松江3路、松江5路、松莘B线"},{"__isset":{"StationName":true,"Updown":true,"SeTime":true,"StationAddress":true,"Stationcode":true,"StrLon02":true,"StrLat02":true,"AssetNumber":true,"LINELIST":true},"StationName":"文汇路人民北路","Updown":0,"SeTime":"21:07-00:18","StationAddress":"上外学生公寓","Stationcode":"SJ0657","StrLon02":121.225482,"StrLat02":31.048172,"AssetNumber":"","LINELIST":"1801路、1802路、1804路、松江18路、松江3路、松江99路、松江DZ3线、松江DZ6线"},{"__isset":{"StationName":true,"Updown":true,"SeTime":true,"StationAddress":true,"Stationcode":true,"StrLon02":true,"StrLat02":true,"AssetNumber":true,"LINELIST":true},"StationName":"龙城路","Updown":0,"SeTime":"21:09-00:20","StationAddress":"文汇路330号","Stationcode":"SJ0658","StrLon02":121.219533,"StrLat02":31.048271,"AssetNumber":"","LINELIST":"1801路、1802路、1804路、松江18路、松江3路、松江99路、松江DZ3线、松江DZ6线、松莘B线、松莘线"},{"__isset":{"StationName":true,"Updown":true,"SeTime":true,"StationAddress":true,"Stationcode":true,"StrLon02":true,"StrLat02":true,"AssetNumber":true,"LINELIST":true},"StationName":"松江大学城","Updown":0,"SeTime":"21:10-00:21","StationAddress":"大学城体育馆","Stationcode":"SJ0717","StrLon02":121.217259,"StrLat02":31.048264,"AssetNumber":"","LINELIST":"1804路、松江3路、松江99路、松莘B线"},{"__isset":{"StationName":true,"Updown":true,"SeTime":true,"StationAddress":true,"Stationcode":true,"StrLon02":true,"StrLat02":true,"AssetNumber":true,"LINELIST":true},"StationName":"文汇路龙腾路","Updown":0,"SeTime":"21:11-00:22","StationAddress":"大学城派出所","Stationcode":"SJ0720","StrLon02":121.214959,"StrLat02":31.048201,"AssetNumber":"","LINELIST":"1801路、1802路、1804路、松江13路、松江17路、松江18路、松江99路、松莘B线、松莘线"},{"__isset":{"StationName":true,"Updown":true,"SeTime":true,"StationAddress":true,"Stationcode":true,"StrLon02":true,"StrLat02":true,"AssetNumber":true,"LINELIST":true},"StationName":"文汇路龙源路","Updown":0,"SeTime":"21:13-00:24","StationAddress":"文汇路816号","Stationcode":"SJ0721","StrLon02":121.20788,"StrLat02":31.048261,"AssetNumber":"","LINELIST":"1801路、1802路、1804路、松江13路、松江17路、松江18路、松江99路、松江DZ3线、松江DZ6线、松莘B线、松莘线"},{"__isset":{"StationName":true,"Updown":true,"SeTime":true,"StationAddress":true,"Stationcode":true,"StrLon02":true,"StrLat02":true,"AssetNumber":true,"LINELIST":true},"StationName":"龙源路文翔路","Updown":0,"SeTime":"21:15-00:26","StationAddress":"文翔路龙源路交叉口北20米","Stationcode":"SJ0731","StrLon02":121.205986,"StrLat02":31.042401,"AssetNumber":"","LINELIST":"1804路、松江13路、松江17路"},{"__isset":{"StationName":true,"Updown":true,"SeTime":true,"StationAddress":true,"Stationcode":true,"StrLon02":true,"StrLat02":true,"AssetNumber":true,"LINELIST":true},"StationName":"立信会计学院","Updown":0,"SeTime":"21:16-00:27","StationAddress":"立信会计学院大门东10米","Stationcode":"SJ0732","StrLon02":121.204378,"StrLat02":31.042267,"AssetNumber":"","LINELIST":"1801路、1804路、松江20路、松江95路"},{"__isset":{"StationName":true,"Updown":true,"SeTime":true,"StationAddress":true,"Stationcode":true,"StrLon02":true,"StrLat02":true,"AssetNumber":true,"LINELIST":true},"StationName":"文翔名苑","Updown":0,"SeTime":"21:18-00:29","StationAddress":"文翔名苑南门西100米","Stationcode":"SJ0733","StrLon02":121.196075,"StrLat02":31.041822,"AssetNumber":"","LINELIST":"1801路、1804路、松江20路、松江95路"},{"__isset":{"StationName":true,"Updown":true,"SeTime":true,"StationAddress":true,"Stationcode":true,"StrLon02":true,"StrLat02":true,"AssetNumber":true,"LINELIST":true},"StationName":"三新北路文翔路","Updown":0,"SeTime":"21:19-00:30","StationAddress":"文翔路三新北路交叉口北100米","Stationcode":"SJ0734","StrLon02":121.194713,"StrLat02":31.042708,"AssetNumber":"","LINELIST":"1804路、1805路、松江15路"},{"__isset":{"StationName":true,"Updown":true,"SeTime":true,"StationAddress":true,"Stationcode":true,"StrLon02":true,"StrLat02":true,"AssetNumber":true,"LINELIST":true},"StationName":"三新北路文宇路","Updown":0,"SeTime":"21:20-00:31","StationAddress":"文宇路口北10米","Stationcode":"SJ0742","StrLon02":121.194229,"StrLat02":31.045009,"AssetNumber":"","LINELIST":"1801路、1804路、1805路、松江15路、松江24路"},{"__isset":{"StationName":true,"Updown":true,"SeTime":true,"StationAddress":true,"Stationcode":true,"StrLon02":true,"StrLat02":true,"AssetNumber":true,"LINELIST":true},"StationName":"三新北路广富林路","Updown":0,"SeTime":"21:21-00:32","StationAddress":"松江大学期六期","Stationcode":"SJ0740","StrLon02":121.193139,"StrLat02":31.050288,"AssetNumber":"","LINELIST":"1801路、1804路、1805路、松江15路、松江24路、松江DZ3线、松江DZ6线"},{"__isset":{"StationName":true,"Updown":true,"SeTime":true,"StationAddress":true,"Stationcode":true,"StrLon02":true,"StrLat02":true,"AssetNumber":true,"LINELIST":true},"StationName":"广富林路三新北路","Updown":0,"SeTime":"21:22-00:33","StationAddress":"广富林路3409号","Stationcode":"SJ0769","StrLon02":121.195572,"StrLat02":31.05339,"AssetNumber":"","LINELIST":"1801路、1804路、松江15路、松江24路、松江98路、松江99路"},{"__isset":{"StationName":true,"Updown":true,"SeTime":true,"StationAddress":true,"Stationcode":true,"StrLon02":true,"StrLat02":true,"AssetNumber":true,"LINELIST":true},"StationName":"广富林路龙源路","Updown":0,"SeTime":"21:24-00:35","StationAddress":"华东政法大学北门东15米","Stationcode":"SJ0768","StrLon02":121.201642,"StrLat02":31.05662,"AssetNumber":"","LINELIST":"1801路、1804路、松江15路、松江24路、松江98路、松江99路、松江DZ9线"},{"__isset":{"StationName":true,"Updown":true,"SeTime":true,"StationAddress":true,"Stationcode":true,"StrLon02":true,"StrLat02":true,"AssetNumber":true,"LINELIST":true},"StationName":"龙源路广富林路","Updown":0,"SeTime":"21:26-00:37","StationAddress":"华东政法大学东门南20米","Stationcode":"SJ0723","StrLon02":121.205944,"StrLat02":31.053452,"AssetNumber":"","LINELIST":"1801路、1802路、1804路、松江33路、松江95路、松江99路"},{"__isset":{"StationName":true,"Updown":true,"SeTime":true,"StationAddress":true,"Stationcode":true,"StrLon02":true,"StrLat02":true,"AssetNumber":true,"LINELIST":true},"StationName":"文汇路龙源路","Updown":0,"SeTime":"21:28-00:39","StationAddress":"上海视觉艺术学院体育场","Stationcode":"SJ0726","StrLon02":121.207829,"StrLat02":31.048131,"AssetNumber":"","LINELIST":"1801路、1802路、1804路、松江13路、松江17路、松江18路、松江99路、松莘B线、松莘线"},{"__isset":{"StationName":true,"Updown":true,"SeTime":true,"StationAddress":true,"Stationcode":true,"StrLon02":true,"StrLat02":true,"AssetNumber":true,"LINELIST":true},"StationName":"文汇路龙腾路","Updown":0,"SeTime":"21:29-00:40","StationAddress":"文汇路840号对面","Stationcode":"SJ0727","StrLon02":121.213674,"StrLat02":31.04817,"AssetNumber":"","LINELIST":"1801路、1802路、1804路、松江13路、松江17路、松江18路、松江99路、松莘B线、松莘线"},{"__isset":{"StationName":true,"Updown":true,"SeTime":true,"StationAddress":true,"Stationcode":true,"StrLon02":true,"StrLat02":true,"AssetNumber":true,"LINELIST":true},"StationName":"松江大学城","Updown":0,"SeTime":"21:30-00:41","StationAddress":"大学城体育馆","Stationcode":"SJ0716","StrLon02":121.217122,"StrLat02":31.04816,"AssetNumber":"","LINELIST":"1804路、松江3路、松江99路、松莘B线"},{"__isset":{"StationName":true,"Updown":true,"SeTime":true,"StationAddress":true,"Stationcode":true,"StrLon02":true,"StrLat02":true,"AssetNumber":true,"LINELIST":true},"StationName":"龙城路","Updown":0,"SeTime":"21:31-00:42","StationAddress":"外贸学院","Stationcode":"SJ0655","StrLon02":121.222056,"StrLat02":31.048081,"AssetNumber":"","LINELIST":"1801路、1802路、1804路、松江18路、松江3路、松江99路、松莘B线、松莘线"},{"__isset":{"StationName":true,"Updown":true,"SeTime":true,"StationAddress":true,"Stationcode":true,"StrLon02":true,"StrLat02":true,"AssetNumber":true,"LINELIST":true},"StationName":"文汇路人民北路","Updown":0,"SeTime":"21:32-00:43","StationAddress":"上外学生公寓","Stationcode":"SJ0656","StrLon02":121.225629,"StrLat02":31.048119,"AssetNumber":"","LINELIST":"1801路、1802路、1804路、松江18路、松江3路、松江99路"},{"__isset":{"StationName":true,"Updown":true,"SeTime":true,"StationAddress":true,"Stationcode":true,"StrLon02":true,"StrLat02":true,"AssetNumber":true,"LINELIST":true},"StationName":"梅家浜路人民北路","Updown":0,"SeTime":"21:34-00:45","StationAddress":"龙马路口西100米","Stationcode":"SJ0707","StrLon02":121.230482,"StrLat02":31.052187,"AssetNumber":"","LINELIST":"1802路、1804路、松江3路、松江5路、松莘B线"},{"__isset":{"StationName":true,"Updown":true,"SeTime":true,"StationAddress":true,"Stationcode":true,"StrLon02":true,"StrLat02":true,"AssetNumber":true,"LINELIST":true},"StationName":"梅家浜路嘉松公路","Updown":0,"SeTime":"21:35-00:46","StationAddress":"梅家浜路1567弄50号","Stationcode":"SJ0708","StrLon02":121.234675,"StrLat02":31.050905,"AssetNumber":"","LINELIST":"1802路、1804路、松江24路、松江3路、松江5路、松莘B线"},{"__isset":{"StationName":true,"Updown":true,"SeTime":true,"StationAddress":true,"Stationcode":true,"StrLon02":true,"StrLat02":true,"AssetNumber":true,"LINELIST":true},"StationName":"客运中心北站","Updown":0,"SeTime":"21:40-00:51","StationAddress":"大学城地铁站","Stationcode":"SJ0669","StrLon02":121.237355,"StrLat02":31.054684,"AssetNumber":"","LINELIST":"1803路、1804路、松江13路、松江16路、松江21路、松江24路、松江3路、松江66路、松江7路、松江9路"}],"Linelatlon":"121.237355,31.054684;121.23734,31.055095;121.237331,31.055508;121.237312,31.055911;121.237303,31.056313;121.237294,31.056726;121.237277,31.057131;121.236825,31.057199;121.236375,31.05726;121.23597,31.057457;121.235425,31.057403;121.234926,31.057485;121.234417,31.057567;121.233916,31.057639;121.233407,31.057711;121.232906,31.057792;121.232407,31.057874;121.231898,31.057945;121.231886,31.057513;121.231875,31.057091;121.231864,31.056658;121.231786,31.056276;121.231851,31.055793;121.23186,31.05535;121.231859,31.054918;121.231868,31.054476;121.231877,31.054033;121.231876,31.0536;121.231885,31.053158;121.231885,31.052726;121.231893,31.052283;121.231899,31.051846;121.231462,31.052013;121.231035,31.052178;121.230482,31.052187;121.230164,31.052466;121.229773,31.052499;121.229392,31.05257;121.228993,31.052612;121.228601,31.052661;121.228124,31.052664;121.227643,31.052675;121.227163,31.052676;121.226687,31.052682;121.226682,31.052264;121.22669,31.051842;121.226689,31.05143;121.226688,31.051007;121.226687,31.050595;121.226685,31.050172;121.226686,31.049771;121.226685,31.049378;121.226684,31.048976;121.226683,31.048574;121.226688,31.04818;121.226282,31.048173;121.225882,31.048173;121.225629,31.048119;121.224981,31.048175;121.224481,31.048176;121.223981,31.048178;121.223491,31.048178;121.22299,31.04818;121.222491,31.048181;121.22199,31.048181;121.221489,31.048193;121.22099,31.048194;121.220489,31.048194;121.219989,31.048195;121.219533,31.048271;121.219048,31.048197;121.218608,31.048209;121.218158,31.048209;121.217718,31.04821;121.217259,31.048264;121.216807,31.048222;121.216347,31.048223;121.215885,31.048224;121.215426,31.048224;121.214959,31.048201;121.214445,31.048227;121.213925,31.048227;121.213404,31.048228;121.212894,31.048219;121.212374,31.048221;121.211862,31.048221;121.211341,31.048223;121.210862,31.048223;121.210382,31.048224;121.209901,31.048224;121.209421,31.048226;121.20895,31.048226;121.20847,31.048227;121.207989,31.048228;121.207509,31.048229;121.207028,31.04823;121.206548,31.04823;121.206071,31.048226;121.206067,31.047779;121.206076,31.047336;121.206075,31.046883;121.206073,31.046442;121.206072,31.045999;121.206071,31.045546;121.206076,31.045104;121.206069,31.044692;121.206068,31.044289;121.206067,31.043877;121.206068,31.043465;121.206065,31.043042;121.206054,31.04262;121.205986,31.042401;121.205532,31.042198;121.205012,31.042199;121.204378,31.042267;121.20398,31.042203;121.203511,31.042212;121.20303,31.042212;121.20256,31.042213;121.202078,31.042224;121.201608,31.042225;121.201138,31.042226;121.200657,31.042227;121.200184,31.042235;121.199817,31.042218;121.199456,31.042208;121.199085,31.042196;121.198584,31.042159;121.198093,31.042127;121.197653,31.04207;121.197209,31.042022;121.196931,31.04198;121.196652,31.041948;121.196075,31.041822;121.195721,31.041791;121.19525,31.041711;121.194787,31.041626;121.19471,31.041984;121.194641,31.042336;121.194713,31.042708;121.194482,31.04307;121.194413,31.043453;121.194334,31.043836;121.194255,31.044217;121.194176,31.0446;121.194229,31.045009;121.194017,31.045415;121.193928,31.045858;121.193839,31.04629;121.193749,31.046732;121.193661,31.047165;121.193578,31.047604;121.193503,31.04794;121.193424,31.048272;121.193353,31.048614;121.193279,31.048946;121.193205,31.049309;121.193126,31.04968;121.193057,31.050043;121.193139,31.050288;121.192905,31.050773;121.192819,31.05121;121.19273,31.051652;121.192639,31.052097;121.193053,31.052306;121.193473,31.052505;121.193894,31.052717;121.194304,31.052916;121.194727,31.053127;121.195148,31.053328;121.195572,31.05339;121.196009,31.053759;121.19645,31.05398;121.196892,31.0542;121.197333,31.054421;121.197784,31.054642;121.198224,31.054861;121.198666,31.055082;121.199117,31.055302;121.199558,31.055523;121.199999,31.055744;121.20044,31.055974;121.200891,31.056195;121.201332,31.056416;121.201642,31.05662;121.202224,31.056857;121.202675,31.057076;121.203127,31.057308;121.203577,31.057528;121.204023,31.057751;121.204359,31.057919;121.2047,31.05808;121.205038,31.058243;121.2053,31.05835;121.205568,31.058452;121.205842,31.058543;121.206055,31.058599;121.206061,31.058168;121.20606,31.057725;121.206059,31.057293;121.206058,31.056861;121.206057,31.056428;121.206061,31.055991;121.206064,31.055603;121.206073,31.05521;121.206072,31.054828;121.206083,31.054438;121.206081,31.054094;121.206091,31.053743;121.205944,31.053452;121.206089,31.052958;121.206088,31.052526;121.206086,31.052093;121.206076,31.051661;121.206075,31.051228;121.206074,31.050786;121.206073,31.050353;121.206072,31.049921;121.206071,31.049489;121.20607,31.049056;121.206069,31.048613;121.206063,31.048182;121.206527,31.04818;121.206998,31.048179;121.207459,31.048179;121.207829,31.048131;121.2084,31.048177;121.208862,31.048181;121.209341,31.048175;121.209821,31.048174;121.210301,31.048174;121.210779,31.048168;121.211262,31.048171;121.211742,31.048171;121.212223,31.04817;121.212714,31.048169;121.213194,31.048169;121.213674,31.04817;121.214164,31.048166;121.214655,31.048166;121.215155,31.048165;121.215646,31.048163;121.216137,31.048163;121.216626,31.048162;121.217122,31.04816;121.217608,31.04816;121.218097,31.048149;121.218588,31.048148;121.219078,31.048147;121.219569,31.048146;121.220048,31.048135;121.220539,31.048135;121.22103,31.048133;121.221519,31.048133;121.222056,31.048081;121.2225,31.04813;121.22298,31.04813;121.223471,31.048128;121.223961,31.048127;121.224451,31.048136;121.224941,31.048135;121.225421,31.048135;121.225912,31.048133;121.226402,31.048132;121.226891,31.048138;121.226883,31.048583;121.226884,31.049026;121.226875,31.049469;121.226876,31.049911;121.226867,31.050354;121.226868,31.050806;121.22686,31.051248;121.226851,31.051691;121.226851,31.052134;121.226846,31.052578;121.227282,31.052585;121.227718,31.052591;121.228144,31.052573;121.228568,31.052562;121.228913,31.052521;121.229264,31.05249;121.229611,31.052449;121.229963,31.052358;121.230323,31.052277;121.23068,31.052185;121.231137,31.052047;121.231547,31.051891;121.231922,31.05174;121.232302,31.051588;121.232674,31.05144;121.232952,31.051345;121.233221,31.051244;121.23349,31.051173;121.233769,31.051098;121.234231,31.051006;121.234675,31.050905;121.235081,31.050908;121.235526,31.050863;121.23597,31.050855;121.23642,31.050844;121.23686,31.050843;121.237305,31.050834;121.237301,31.051223;121.237292,31.051606;121.237292,31.051998;121.237283,31.052391;121.237285,31.052773;121.237275,31.053164;121.237269,31.053549;121.237546,31.053596;121.237547,31.053927;121.237548,31.054249;121.237544,31.05458;121.237366,31.054623","TicketPrice":"1元"}]