[{"RoadLine":"1801路","Startstation1":"松江大学城","Startbegintime1":"06:00","Startendtime1":"21:30","Startstation2":"松江大学城","Startbegintime2":"06:00","Startendtime2":"21:30"},{"RoadLine":"1802路","Startstation1":"大学城枢纽站","Startbegintime1":"06:30","Startendtime1":"20:30","Startstation2":"大学城枢纽站","Startbegintime2":"06:30","Startendtime2":"20:30"},{"RoadLine":"1803路","Startstation1":"松江客运中心","Startbegintime1":"06:00","Startendtime1":"21:00","Startstation2":"松江客运中心","Startbegintime2":"06:00","Startendtime2":"21:00"},{"RoadLine":"1804路","Startstation1":"松江客运中心","Startbegintime1":"21:00","Startendtime1":"00:11","Startstation2":"松江客运中心","Startbegintime2":"21:00","Startendtime2":"00:11"},{"RoadLine":"1805路","Startstation1":"西部工业园区公交站","Startbegintime1":"06:00","Startendtime1":"18:00","Startstation2":"文翔路站","Startbegintime2":"06:00","Startendtime2":"18:00"},{"RoadLine":"1806路","Startstation1":"西部工业园公交站","Startbegintime1":"06:00","Startendtime1":"18:00","Startstation2":"小昆山公交枢纽站","Startbegintime2":"06:25","Startendtime2":"18:25"},{"RoadLine":"1807路","Startstation1":"松江枢纽","Startbegintime1":"21:00","Startendtime1":"00:45","Startstation2":"松江枢纽","Startbegintime2":"21:00","Startendtime2":"00:45"},{"RoadLine":"1809路","Startstation1":"松江新城地铁站","Startbegintime1":"21:00","Startendtime1":"00:15","Startstation2":"松江新城地铁站","Startbegintime2":"21:00","Startendtime2":"00:15"},{"RoadLine":"1810路","Startstation1":"松江汽车西站","Startbegintime1":"06:00","Startendtime1":"20:30","Startstation2":"文翔路站","Startbegintime2":"06:30","Startendtime2":"21:00"},{"RoadLine":"1812路","Startstation1":"新桥站","Startbegintime1":"06:00","Startendtime1":"21:00","Startstation2":"新桥站","Startbegintime2":"06:00","Startendtime2":"21:00"},{"RoadLine":"1813路","Startstation1":"新桥站","Startbegintime1":"06:00","Startendtime1":"21:00","Startstation2":"新桥站","Startbegintime2":"06:00","Startendtime2":"21:00"},{"RoadLine":"1814路","Startstation1":"春申枢纽站","Startbegintime1":"06:25","Startendtime1":"20:50","Startstation2":"漕河泾开发区松江园区","Startbegintime2":"06:00","Startendtime2":"20:20"},{"RoadLine":"1816路","Startstation1":"松江汽车西站","Startbegintime1":"06:00","Startendtime1":"21:00","Startstation2":"松江汽车西站","Startbegintime2":"06:00","Startendtime2":"21:00"},{"RoadLine":"1817路","Startstation1":"晨星小区","Startbegintime1":"06:00","Startendtime1":"21:00","Startstation2":"晨星小区","Startbegintime2":"06:00","Startendtime2":"21:00"},{"RoadLine":"1820路","Startstation1":"车墩公交枢纽站","Startbegintime1":"06:00","Startendtime1":"18:50","Startstation2":"香泾路泾车路","Startbegintime2":"06:20","Startendtime2":"19:10"},{"RoadLine":"1822路","Startstation1":"东兴路公交站","Startbegintime1":"07:30","Startendtime1":"18:00","Startstation2":"东兴路公交站","Startbegintime2":"07:30","Startendtime2":"18:00"},{"RoadLine":"1825路","Startstation1":"叶榭站","Startbegintime1":"06:00","Startendtime1":"21:15","Startstation2":"叶榭站","Startbegintime2":"06:00","Startendtime2":"21:15"},{"RoadLine":"1826路","Startstation1":"叶榭站","Startbegintime1":"06:00","Startendtime1":"19:00","Startstation2":"大叶公路东勤公路","Startbegintime2":"06:20","Startendtime2":"19:20"},{"RoadLine":"1840路","Startstation1":"九亭地铁站","Startbegintime1":"06:00","Startendtime1":"23:30","Startstation2":"九亭地铁站","Startbegintime2":"06:00","Startendtime2":"23:30"},{"RoadLine":"1841路","Startstation1":"九亭地铁站","Startbegintime1":"06:45","Startendtime1":"23:30","Startstation2":"九亭地铁站","Startbegintime2":"06:45","Startendtime2":"23:30"},{"RoadLine":"1842路","Startstation1":"漕河泾开发区松江园区","Startbegintime1":"06:50","Startendtime1":"18:30","Startstation2":"漕河泾开发区松江园区","Startbegintime2":"06:50","Startendtime2":"18:30"},{"RoadLine":"1843路","Startstation1":"九亭地铁站","Startbegintime1":"06:00","Startendtime1":"23:30","Startstation2":"九亭地铁站","Startbegintime2":"06:00","Startendtime2":"23:30"},{"RoadLine":"1845路","Startstation1":"泗泾汽车站","Startbegintime1":"06:00","Startendtime1":"23:00","Startstation2":"泗泾汽车站","Startbegintime2":"06:00","Startendtime2":"23:00"},{"RoadLine":"1845路区间","Startstation1":"横港公路古楼公路","Startbegintime1":"7:30","Startendtime1":"15:50","Startstation2":"横港公路古楼公路","Startbegintime2":"7:30","Startendtime2":"15:50"},{"RoadLine":"1846路","Startstation1":"泗泾汽车站","Startbegintime1":"06:15","Startendtime1":"20:50","Startstation2":"泗泾汽车站","Startbegintime2":"06:15","Startendtime2":"20:50"},{"RoadLine":"1849路","Startstation1":"东三轮渡","Startbegintime1":"06:40","Startendtime1":"18:00","Startstation2":"松江枢纽","Startbegintime2":"06:00","Startendtime2":"17:10"}]